{"name": "sensi-repository", "path": "\\scanners\\PerFolder\\sensi-repository.py", "type": "REQUEST", "hostname": "sqli-labs.bachang.org", "url": "https://sqli-labs.bachang.org/.git/config", "vultype": "SENSITIVE", "createtime": "2025-05-18 11:49:17", "detail": {"Request1": [{"position": null, "request": "GET https://sqli-labs.bachang.org/.git/config HTTP/1.1\nUser-Agent: Mozilla/5.0 (Windows NT 6.1; WOW64) AppleWebKit/537.36 (KHTML, like Gecko) Chrome/30.0.1599.101\nAccept-Encoding: gzip, deflate, br, zstd\nAccept: */*\nConnection: close\nHost: sqli-labs.bachang.org\n\n", "response": "HTTP/1.1 200 OK\r\nServer: openresty\r\nDate: Sun, 18 May 2025 03:49:17 GMT\r\nTransfer-Encoding: chunked\r\nConnection: close\r\nAccept-Ranges: bytes\r\nCache-Control: no-cache\r\nStrict-Transport-Security: max-age=31536000\r\n\r\n[core]\n\trepositoryformatversion = 0\n\tfilemode = true\n\tbare = false\n\tlogallrefupdates = true\n[remote \"origin\"]\n\turl = https://github.com/Audi-1/sqli-labs\n\tfetch = +refs/heads/*:refs/remotes/origin/*\n[branch \"master\"]\n\tremote = origin\n\tmerge = refs/heads/master\n", "desc": "repositoryformatversion[\\s\\S]*"}]}, "show": null}
